[ {
  "first_name" : "Isla",
  "last_name" : "Evans",
  "date_time" : "2023-11-10T11:43:19.694+00:00",
  "type" : "YIELD_FAIL",
  "fine_amount" : 880.0
}, {
  "first_name" : "John",
  "last_name" : "Brown",
  "date_time" : "2022-12-21T18:26:06.694+00:00",
  "type" : "UNDER_INFLUENCE",
  "fine_amount" : 856.0
}, {
  "first_name" : "Taylor",
  "last_name" : "Evans",
  "date_time" : "2023-02-13T17:29:25.694+00:00",
  "type" : "INVALID_LICENSE",
  "fine_amount" : 955.0
}, {
  "first_name" : "Constantine",
  "last_name" : "Black",
  "date_time" : "2023-07-08T00:44:46.694+00:00",
  "type" : "FELONY",
  "fine_amount" : 641.0
}, {
  "first_name" : "Charlie",
  "last_name" : "O'Neill",
  "date_time" : "2023-09-21T04:03:39.694+00:00",
  "type" : "UNDER_INFLUENCE",
  "fine_amount" : 711.0
}, {
  "first_name" : "Amelia",
  "last_name" : "White",
  "date_time" : "2023-03-10T09:20:30.694+00:00",
  "type" : "RED_LIGHT_RUN",
  "fine_amount" : 648.0
}, {
  "first_name" : "Oliver",
  "last_name" : "Jackson",
  "date_time" : "2023-10-30T09:43:58.694+00:00",
  "type" : "RED_LIGHT_RUN",
  "fine_amount" : 707.0
}, {
  "first_name" : "Daniela",
  "last_name" : "O'Kelly",
  "date_time" : "2023-01-24T10:38:03.694+00:00",
  "type" : "FELONY",
  "fine_amount" : 550.0
}, {
  "first_name" : "Taylor",
  "last_name" : "Jackson",
  "date_time" : "2023-06-22T04:16:32.694+00:00",
  "type" : "RECKLESS",
  "fine_amount" : 738.0
}, {
  "first_name" : "Mark",
  "last_name" : "Jackson",
  "date_time" : "2023-07-27T17:47:24.694+00:00",
  "type" : "FELONY",
  "fine_amount" : 515.0
}, {
  "first_name" : "Isla",
  "last_name" : "Smith",
  "date_time" : "2023-09-30T06:27:28.694+00:00",
  "type" : "YIELD_FAIL",
  "fine_amount" : 918.0
}, {
  "first_name" : "Jacob",
  "last_name" : "White",
  "date_time" : "2023-07-20T05:42:32.694+00:00",
  "type" : "YIELD_FAIL",
  "fine_amount" : 676.0
}, {
  "first_name" : "Harry",
  "last_name" : "Davis",
  "date_time" : "2023-06-20T13:06:02.694+00:00",
  "type" : "UNDER_INFLUENCE",
  "fine_amount" : 578.0
}, {
  "first_name" : "Isabella",
  "last_name" : "Archer",
  "date_time" : "2023-08-08T02:44:07.694+00:00",
  "type" : "RECKLESS",
  "fine_amount" : 814.0
}, {
  "first_name" : "George",
  "last_name" : "Robinson",
  "date_time" : "2023-02-12T10:10:42.694+00:00",
  "type" : "INVALID_LICENSE",
  "fine_amount" : 658.0
}, {
  "first_name" : "William",
  "last_name" : "Archer",
  "date_time" : "2023-09-25T00:55:56.694+00:00",
  "type" : "RED_LIGHT_RUN",
  "fine_amount" : 507.0
}, {
  "first_name" : "Jane",
  "last_name" : "Johnson",
  "date_time" : "2022-12-02T19:36:05.694+00:00",
  "type" : "YIELD_FAIL",
  "fine_amount" : 823.0
}, {
  "first_name" : "Joe",
  "last_name" : "O'Brien",
  "date_time" : "2023-03-20T21:41:25.694+00:00",
  "type" : "RED_LIGHT_RUN",
  "fine_amount" : 852.0
}, {
  "first_name" : "Joe",
  "last_name" : "O'Brien",
  "date_time" : "2023-09-06T17:08:23.694+00:00",
  "type" : "UNDER_INFLUENCE",
  "fine_amount" : 645.0
}, {
  "first_name" : "Jean",
  "last_name" : "Blake",
  "date_time" : "2023-03-12T16:55:28.694+00:00",
  "type" : "RECKLESS",
  "fine_amount" : 517.0
}, {
  "first_name" : "Arthur",
  "last_name" : "Blake",
  "date_time" : "2023-04-15T17:04:03.694+00:00",
  "type" : "RECKLESS",
  "fine_amount" : 783.0
}, {
  "first_name" : "Charles",
  "last_name" : "Peterson",
  "date_time" : "2023-09-04T11:57:52.694+00:00",
  "type" : "INVALID_LICENSE",
  "fine_amount" : 930.0
}, {
  "first_name" : "Louis",
  "last_name" : "White",
  "date_time" : "2023-07-27T20:33:46.694+00:00",
  "type" : "RECKLESS",
  "fine_amount" : 660.0
}, {
  "first_name" : "Isabella",
  "last_name" : "Black",
  "date_time" : "2023-05-19T02:09:47.694+00:00",
  "type" : "YIELD_FAIL",
  "fine_amount" : 893.0
}, {
  "first_name" : "Isabella",
  "last_name" : "White",
  "date_time" : "2023-06-17T21:31:25.694+00:00",
  "type" : "FELONY",
  "fine_amount" : 858.0
}, {
  "first_name" : "Amelia",
  "last_name" : "Robinson",
  "date_time" : "2023-04-19T19:07:29.694+00:00",
  "type" : "UNDER_INFLUENCE",
  "fine_amount" : 749.0
}, {
  "first_name" : "Ivan",
  "last_name" : "Blake",
  "date_time" : "2023-10-13T16:00:30.694+00:00",
  "type" : "RECKLESS",
  "fine_amount" : 907.0
}, {
  "first_name" : "Arthur",
  "last_name" : "Jackson",
  "date_time" : "2023-05-13T04:02:39.694+00:00",
  "type" : "UNDER_INFLUENCE",
  "fine_amount" : 704.0
}, {
  "first_name" : "George",
  "last_name" : "Brown",
  "date_time" : "2023-01-01T12:22:27.694+00:00",
  "type" : "UNDER_INFLUENCE",
  "fine_amount" : 978.0
}, {
  "first_name" : "Max",
  "last_name" : "O'Neill",
  "date_time" : "2023-07-11T09:49:33.694+00:00",
  "type" : "RED_LIGHT_RUN",
  "fine_amount" : 938.0
}, {
  "first_name" : "Louis",
  "last_name" : "Jackson",
  "date_time" : "2023-02-19T05:14:22.694+00:00",
  "type" : "UNDER_INFLUENCE",
  "fine_amount" : 780.0
}, {
  "first_name" : "William",
  "last_name" : "Evans",
  "date_time" : "2023-07-01T10:36:48.694+00:00",
  "type" : "RED_LIGHT_RUN",
  "fine_amount" : 694.0
}, {
  "first_name" : "Zoe",
  "last_name" : "Davis",
  "date_time" : "2023-07-31T17:53:57.694+00:00",
  "type" : "RED_LIGHT_RUN",
  "fine_amount" : 854.0
}, {
  "first_name" : "James",
  "last_name" : "Davis",
  "date_time" : "2023-02-20T15:14:34.694+00:00",
  "type" : "RED_LIGHT_RUN",
  "fine_amount" : 581.0
}, {
  "first_name" : "Max",
  "last_name" : "Roberts",
  "date_time" : "2022-12-06T21:22:56.694+00:00",
  "type" : "UNDER_INFLUENCE",
  "fine_amount" : 646.0
}, {
  "first_name" : "Maxwell",
  "last_name" : "Jackson",
  "date_time" : "2023-08-11T10:06:06.694+00:00",
  "type" : "RED_LIGHT_RUN",
  "fine_amount" : 577.0
}, {
  "first_name" : "Isla",
  "last_name" : "O'Neill",
  "date_time" : "2022-12-23T08:55:19.694+00:00",
  "type" : "INVALID_LICENSE",
  "fine_amount" : 981.0
}, {
  "first_name" : "Jack",
  "last_name" : "O'Neill",
  "date_time" : "2023-06-12T01:52:37.694+00:00",
  "type" : "FELONY",
  "fine_amount" : 819.0
}, {
  "first_name" : "Charlie",
  "last_name" : "Robinson",
  "date_time" : "2023-11-24T15:54:23.694+00:00",
  "type" : "UNDER_INFLUENCE",
  "fine_amount" : 817.0
}, {
  "first_name" : "Charlie",
  "last_name" : "Evans",
  "date_time" : "2023-01-05T10:45:53.694+00:00",
  "type" : "RED_LIGHT_RUN",
  "fine_amount" : 912.0
}, {
  "first_name" : "Maxwell",
  "last_name" : "Davis",
  "date_time" : "2023-07-04T18:11:27.694+00:00",
  "type" : "INVALID_LICENSE",
  "fine_amount" : 584.0
}, {
  "first_name" : "Jacob",
  "last_name" : "Smith",
  "date_time" : "2023-08-17T08:30:30.694+00:00",
  "type" : "UNDER_INFLUENCE",
  "fine_amount" : 593.0
}, {
  "first_name" : "Jack",
  "last_name" : "Jackson",
  "date_time" : "2023-11-15T13:23:18.694+00:00",
  "type" : "UNDER_INFLUENCE",
  "fine_amount" : 587.0
}, {
  "first_name" : "Isla",
  "last_name" : "Blake",
  "date_time" : "2023-03-12T18:38:37.694+00:00",
  "type" : "YIELD_FAIL",
  "fine_amount" : 993.0
}, {
  "first_name" : "Max",
  "last_name" : "Smith",
  "date_time" : "2023-06-24T23:17:40.694+00:00",
  "type" : "YIELD_FAIL",
  "fine_amount" : 783.0
}, {
  "first_name" : "John",
  "last_name" : "Roberts",
  "date_time" : "2023-07-17T14:23:03.694+00:00",
  "type" : "FELONY",
  "fine_amount" : 637.0
}, {
  "first_name" : "Oliver",
  "last_name" : "Blake",
  "date_time" : "2023-07-22T14:58:32.694+00:00",
  "type" : "INVALID_LICENSE",
  "fine_amount" : 754.0
}, {
  "first_name" : "Oscar",
  "last_name" : "Peterson",
  "date_time" : "2023-09-03T15:21:09.694+00:00",
  "type" : "YIELD_FAIL",
  "fine_amount" : 881.0
}, {
  "first_name" : "Taylor",
  "last_name" : "O'Neill",
  "date_time" : "2023-05-12T04:09:45.694+00:00",
  "type" : "FELONY",
  "fine_amount" : 991.0
}, {
  "first_name" : "George",
  "last_name" : "Davis",
  "date_time" : "2023-09-12T15:04:55.694+00:00",
  "type" : "RECKLESS",
  "fine_amount" : 914.0
}, {
  "first_name" : "Constantine",
  "last_name" : "Evans",
  "date_time" : "2023-03-01T08:22:02.694+00:00",
  "type" : "FELONY",
  "fine_amount" : 685.0
}, {
  "first_name" : "Zoe",
  "last_name" : "Taylor",
  "date_time" : "2023-03-07T19:48:01.694+00:00",
  "type" : "INVALID_LICENSE",
  "fine_amount" : 878.0
}, {
  "first_name" : "Constantine",
  "last_name" : "Brown",
  "date_time" : "2023-08-14T00:23:41.694+00:00",
  "type" : "INVALID_LICENSE",
  "fine_amount" : 591.0
}, {
  "first_name" : "Oliver",
  "last_name" : "Roberts",
  "date_time" : "2023-03-24T10:23:23.694+00:00",
  "type" : "UNDER_INFLUENCE",
  "fine_amount" : 914.0
}, {
  "first_name" : "Arthur",
  "last_name" : "Blake",
  "date_time" : "2023-03-16T15:39:19.694+00:00",
  "type" : "RED_LIGHT_RUN",
  "fine_amount" : 764.0
}, {
  "first_name" : "John",
  "last_name" : "Taylor",
  "date_time" : "2023-01-09T16:15:22.694+00:00",
  "type" : "RECKLESS",
  "fine_amount" : 998.0
}, {
  "first_name" : "Emily",
  "last_name" : "Johnson",
  "date_time" : "2023-11-18T00:34:00.694+00:00",
  "type" : "RECKLESS",
  "fine_amount" : 590.0
}, {
  "first_name" : "Joe",
  "last_name" : "Archer",
  "date_time" : "2023-04-07T05:13:05.694+00:00",
  "type" : "RED_LIGHT_RUN",
  "fine_amount" : 832.0
}, {
  "first_name" : "Constantine",
  "last_name" : "Peterson",
  "date_time" : "2023-09-11T16:56:43.694+00:00",
  "type" : "RED_LIGHT_RUN",
  "fine_amount" : 749.0
}, {
  "first_name" : "Amelia",
  "last_name" : "Peterson",
  "date_time" : "2023-03-20T17:25:30.694+00:00",
  "type" : "YIELD_FAIL",
  "fine_amount" : 596.0
}, {
  "first_name" : "Charles",
  "last_name" : "Smith",
  "date_time" : "2023-11-18T23:58:22.694+00:00",
  "type" : "INVALID_LICENSE",
  "fine_amount" : 640.0
}, {
  "first_name" : "James",
  "last_name" : "White",
  "date_time" : "2023-04-05T09:36:07.694+00:00",
  "type" : "INVALID_LICENSE",
  "fine_amount" : 860.0
}, {
  "first_name" : "George",
  "last_name" : "Evans",
  "date_time" : "2023-01-16T06:39:43.694+00:00",
  "type" : "YIELD_FAIL",
  "fine_amount" : 801.0
}, {
  "first_name" : "Maxwell",
  "last_name" : "Evans",
  "date_time" : "2023-09-16T02:23:02.694+00:00",
  "type" : "FELONY",
  "fine_amount" : 541.0
}, {
  "first_name" : "George",
  "last_name" : "Taylor",
  "date_time" : "2023-11-15T10:18:31.694+00:00",
  "type" : "YIELD_FAIL",
  "fine_amount" : 789.0
}, {
  "first_name" : "Taylor",
  "last_name" : "Evans",
  "date_time" : "2023-05-15T05:12:06.694+00:00",
  "type" : "FELONY",
  "fine_amount" : 643.0
}, {
  "first_name" : "Maxwell",
  "last_name" : "Wilson",
  "date_time" : "2023-07-14T20:49:07.694+00:00",
  "type" : "UNDER_INFLUENCE",
  "fine_amount" : 986.0
}, {
  "first_name" : "Daniel",
  "last_name" : "O'Kelly",
  "date_time" : "2023-11-10T08:36:53.694+00:00",
  "type" : "UNDER_INFLUENCE",
  "fine_amount" : 622.0
}, {
  "first_name" : "Isla",
  "last_name" : "Wilson",
  "date_time" : "2023-08-10T16:20:03.694+00:00",
  "type" : "RECKLESS",
  "fine_amount" : 957.0
}, {
  "first_name" : "Jane",
  "last_name" : "White",
  "date_time" : "2023-04-20T10:59:14.694+00:00",
  "type" : "INVALID_LICENSE",
  "fine_amount" : 967.0
}, {
  "first_name" : "George",
  "last_name" : "Taylor",
  "date_time" : "2023-10-27T02:51:07.694+00:00",
  "type" : "UNDER_INFLUENCE",
  "fine_amount" : 887.0
}, {
  "first_name" : "Daniel",
  "last_name" : "Davis",
  "date_time" : "2023-02-06T14:46:52.694+00:00",
  "type" : "UNDER_INFLUENCE",
  "fine_amount" : 766.0
}, {
  "first_name" : "James",
  "last_name" : "Evans",
  "date_time" : "2023-10-17T09:30:21.694+00:00",
  "type" : "FELONY",
  "fine_amount" : 879.0
}, {
  "first_name" : "Daniel",
  "last_name" : "Peterson",
  "date_time" : "2023-09-01T10:36:23.694+00:00",
  "type" : "UNDER_INFLUENCE",
  "fine_amount" : 824.0
}, {
  "first_name" : "Isla",
  "last_name" : "Black",
  "date_time" : "2023-01-08T15:21:16.694+00:00",
  "type" : "FELONY",
  "fine_amount" : 536.0
}, {
  "first_name" : "William",
  "last_name" : "O'Kelly",
  "date_time" : "2023-08-03T20:45:04.694+00:00",
  "type" : "INVALID_LICENSE",
  "fine_amount" : 798.0
}, {
  "first_name" : "Constantine",
  "last_name" : "Davis",
  "date_time" : "2023-11-04T02:54:02.694+00:00",
  "type" : "INVALID_LICENSE",
  "fine_amount" : 928.0
}, {
  "first_name" : "Zoe",
  "last_name" : "O'Connor",
  "date_time" : "2023-02-23T11:52:59.694+00:00",
  "type" : "RECKLESS",
  "fine_amount" : 792.0
}, {
  "first_name" : "Joe",
  "last_name" : "White",
  "date_time" : "2023-02-28T09:08:27.694+00:00",
  "type" : "FELONY",
  "fine_amount" : 616.0
}, {
  "first_name" : "Joe",
  "last_name" : "Davies",
  "date_time" : "2023-07-18T11:54:01.694+00:00",
  "type" : "RECKLESS",
  "fine_amount" : 887.0
}, {
  "first_name" : "Louis",
  "last_name" : "Evans",
  "date_time" : "2023-02-14T11:42:20.694+00:00",
  "type" : "RED_LIGHT_RUN",
  "fine_amount" : 807.0
}, {
  "first_name" : "Harry",
  "last_name" : "Jackson",
  "date_time" : "2023-07-16T17:37:13.694+00:00",
  "type" : "FELONY",
  "fine_amount" : 962.0
}, {
  "first_name" : "Daniela",
  "last_name" : "Wilson",
  "date_time" : "2023-05-20T22:43:52.694+00:00",
  "type" : "YIELD_FAIL",
  "fine_amount" : 629.0
}, {
  "first_name" : "Zoe",
  "last_name" : "Peterson",
  "date_time" : "2023-11-17T12:08:38.694+00:00",
  "type" : "UNDER_INFLUENCE",
  "fine_amount" : 510.0
}, {
  "first_name" : "Jane",
  "last_name" : "Robinson",
  "date_time" : "2023-06-15T06:01:18.694+00:00",
  "type" : "YIELD_FAIL",
  "fine_amount" : 516.0
}, {
  "first_name" : "Harry",
  "last_name" : "White",
  "date_time" : "2023-02-07T01:17:09.694+00:00",
  "type" : "RED_LIGHT_RUN",
  "fine_amount" : 886.0
}, {
  "first_name" : "Jacob",
  "last_name" : "Roberts",
  "date_time" : "2023-01-28T09:19:50.694+00:00",
  "type" : "FELONY",
  "fine_amount" : 700.0
}, {
  "first_name" : "Ivan",
  "last_name" : "O'Neill",
  "date_time" : "2023-08-30T03:22:36.694+00:00",
  "type" : "INVALID_LICENSE",
  "fine_amount" : 765.0
}, {
  "first_name" : "Harry",
  "last_name" : "Blake",
  "date_time" : "2023-06-14T03:27:30.694+00:00",
  "type" : "INVALID_LICENSE",
  "fine_amount" : 780.0
}, {
  "first_name" : "Mark",
  "last_name" : "Peterson",
  "date_time" : "2023-05-21T18:20:10.694+00:00",
  "type" : "RED_LIGHT_RUN",
  "fine_amount" : 597.0
}, {
  "first_name" : "Jean",
  "last_name" : "Blake",
  "date_time" : "2023-04-24T23:16:04.694+00:00",
  "type" : "RECKLESS",
  "fine_amount" : 784.0
}, {
  "first_name" : "Thomas",
  "last_name" : "Davis",
  "date_time" : "2022-12-13T11:58:23.694+00:00",
  "type" : "UNDER_INFLUENCE",
  "fine_amount" : 523.0
}, {
  "first_name" : "Thomas",
  "last_name" : "Brown",
  "date_time" : "2023-06-26T12:42:38.694+00:00",
  "type" : "INVALID_LICENSE",
  "fine_amount" : 828.0
}, {
  "first_name" : "Mark",
  "last_name" : "O'Brien",
  "date_time" : "2023-03-02T07:41:32.694+00:00",
  "type" : "RED_LIGHT_RUN",
  "fine_amount" : 731.0
}, {
  "first_name" : "Jack",
  "last_name" : "Roberts",
  "date_time" : "2023-04-15T03:05:48.694+00:00",
  "type" : "RECKLESS",
  "fine_amount" : 661.0
}, {
  "first_name" : "Oliver",
  "last_name" : "Brown",
  "date_time" : "2023-07-11T12:54:31.694+00:00",
  "type" : "RED_LIGHT_RUN",
  "fine_amount" : 557.0
}, {
  "first_name" : "Emily",
  "last_name" : "Taylor",
  "date_time" : "2023-06-04T10:50:28.694+00:00",
  "type" : "INVALID_LICENSE",
  "fine_amount" : 827.0
}, {
  "first_name" : "Mark",
  "last_name" : "Jackson",
  "date_time" : "2022-12-13T04:11:24.694+00:00",
  "type" : "RECKLESS",
  "fine_amount" : 573.0
}, {
  "first_name" : "Isla",
  "last_name" : "Taylor",
  "date_time" : "2023-03-28T02:13:31.694+00:00",
  "type" : "INVALID_LICENSE",
  "fine_amount" : 503.0
}, {
  "first_name" : "Emily",
  "last_name" : "Evans",
  "date_time" : "2023-02-07T18:23:34.694+00:00",
  "type" : "INVALID_LICENSE",
  "fine_amount" : 924.0
}, {
  "first_name" : "Joe",
  "last_name" : "Smith",
  "date_time" : "2023-01-16T23:41:58.694+00:00",
  "type" : "INVALID_LICENSE",
  "fine_amount" : 758.0
}, {
  "first_name" : "Thomas",
  "last_name" : "Roberts",
  "date_time" : "2022-12-29T02:21:42.694+00:00",
  "type" : "INVALID_LICENSE",
  "fine_amount" : 904.0
}, {
  "first_name" : "George",
  "last_name" : "Jackson",
  "date_time" : "2023-03-11T05:59:14.694+00:00",
  "type" : "FELONY",
  "fine_amount" : 962.0
}, {
  "first_name" : "Jane",
  "last_name" : "O'Neill",
  "date_time" : "2023-09-06T02:15:30.694+00:00",
  "type" : "YIELD_FAIL",
  "fine_amount" : 701.0
}, {
  "first_name" : "Oscar",
  "last_name" : "Archer",
  "date_time" : "2022-12-20T21:14:45.694+00:00",
  "type" : "FELONY",
  "fine_amount" : 954.0
}, {
  "first_name" : "Jack",
  "last_name" : "Taylor",
  "date_time" : "2023-09-14T15:07:22.694+00:00",
  "type" : "UNDER_INFLUENCE",
  "fine_amount" : 587.0
}, {
  "first_name" : "Maxwell",
  "last_name" : "Roberts",
  "date_time" : "2023-04-06T00:57:11.694+00:00",
  "type" : "FELONY",
  "fine_amount" : 778.0
}, {
  "first_name" : "Maxwell",
  "last_name" : "Brown",
  "date_time" : "2023-09-29T09:02:49.694+00:00",
  "type" : "UNDER_INFLUENCE",
  "fine_amount" : 885.0
}, {
  "first_name" : "Amelia",
  "last_name" : "Robinson",
  "date_time" : "2023-04-12T18:09:37.694+00:00",
  "type" : "INVALID_LICENSE",
  "fine_amount" : 940.0
}, {
  "first_name" : "Mark",
  "last_name" : "Evans",
  "date_time" : "2023-10-20T16:03:17.694+00:00",
  "type" : "RED_LIGHT_RUN",
  "fine_amount" : 559.0
}, {
  "first_name" : "Emily",
  "last_name" : "Blake",
  "date_time" : "2023-08-01T18:00:44.694+00:00",
  "type" : "RECKLESS",
  "fine_amount" : 919.0
}, {
  "first_name" : "Joe",
  "last_name" : "O'Connor",
  "date_time" : "2023-04-06T18:24:52.694+00:00",
  "type" : "RED_LIGHT_RUN",
  "fine_amount" : 515.0
}, {
  "first_name" : "Harry",
  "last_name" : "Johnson",
  "date_time" : "2023-06-16T08:34:20.694+00:00",
  "type" : "RED_LIGHT_RUN",
  "fine_amount" : 524.0
}, {
  "first_name" : "Daniel",
  "last_name" : "O'Kelly",
  "date_time" : "2023-08-25T17:11:25.694+00:00",
  "type" : "INVALID_LICENSE",
  "fine_amount" : 975.0
}, {
  "first_name" : "Daniel",
  "last_name" : "Johnson",
  "date_time" : "2022-12-31T19:59:42.694+00:00",
  "type" : "YIELD_FAIL",
  "fine_amount" : 663.0
}, {
  "first_name" : "Harry",
  "last_name" : "Archer",
  "date_time" : "2023-06-23T01:11:33.694+00:00",
  "type" : "FELONY",
  "fine_amount" : 575.0
}, {
  "first_name" : "Emily",
  "last_name" : "Peterson",
  "date_time" : "2023-03-13T22:02:16.694+00:00",
  "type" : "UNDER_INFLUENCE",
  "fine_amount" : 814.0
}, {
  "first_name" : "George",
  "last_name" : "Davis",
  "date_time" : "2023-09-09T06:26:44.694+00:00",
  "type" : "INVALID_LICENSE",
  "fine_amount" : 906.0
}, {
  "first_name" : "Arthur",
  "last_name" : "Archer",
  "date_time" : "2023-06-20T01:07:11.694+00:00",
  "type" : "YIELD_FAIL",
  "fine_amount" : 788.0
}, {
  "first_name" : "Charlie",
  "last_name" : "O'Connor",
  "date_time" : "2023-09-26T17:22:30.694+00:00",
  "type" : "UNDER_INFLUENCE",
  "fine_amount" : 600.0
}, {
  "first_name" : "Jane",
  "last_name" : "Blake",
  "date_time" : "2023-09-10T18:42:14.694+00:00",
  "type" : "UNDER_INFLUENCE",
  "fine_amount" : 753.0
}, {
  "first_name" : "William",
  "last_name" : "O'Brien",
  "date_time" : "2023-01-22T06:59:06.694+00:00",
  "type" : "RED_LIGHT_RUN",
  "fine_amount" : 973.0
}, {
  "first_name" : "Zoe",
  "last_name" : "Wilson",
  "date_time" : "2023-10-08T03:08:19.694+00:00",
  "type" : "RECKLESS",
  "fine_amount" : 822.0
}, {
  "first_name" : "Jean",
  "last_name" : "Taylor",
  "date_time" : "2023-11-27T22:27:20.694+00:00",
  "type" : "FELONY",
  "fine_amount" : 660.0
}, {
  "first_name" : "Jacob",
  "last_name" : "Brown",
  "date_time" : "2023-05-24T05:47:01.694+00:00",
  "type" : "INVALID_LICENSE",
  "fine_amount" : 975.0
}, {
  "first_name" : "William",
  "last_name" : "Peterson",
  "date_time" : "2023-01-07T07:28:43.694+00:00",
  "type" : "RED_LIGHT_RUN",
  "fine_amount" : 529.0
}, {
  "first_name" : "Emily",
  "last_name" : "White",
  "date_time" : "2023-07-21T01:55:09.694+00:00",
  "type" : "RECKLESS",
  "fine_amount" : 874.0
}, {
  "first_name" : "Charlie",
  "last_name" : "Black",
  "date_time" : "2022-12-26T23:49:15.694+00:00",
  "type" : "FELONY",
  "fine_amount" : 520.0
}, {
  "first_name" : "Charlie",
  "last_name" : "O'Connor",
  "date_time" : "2022-12-12T02:37:42.694+00:00",
  "type" : "YIELD_FAIL",
  "fine_amount" : 786.0
}, {
  "first_name" : "Jean",
  "last_name" : "Davis",
  "date_time" : "2023-01-04T10:22:20.694+00:00",
  "type" : "YIELD_FAIL",
  "fine_amount" : 807.0
}, {
  "first_name" : "George",
  "last_name" : "Black",
  "date_time" : "2023-11-09T06:34:44.694+00:00",
  "type" : "INVALID_LICENSE",
  "fine_amount" : 912.0
}, {
  "first_name" : "Isla",
  "last_name" : "O'Connor",
  "date_time" : "2023-01-17T21:58:44.694+00:00",
  "type" : "YIELD_FAIL",
  "fine_amount" : 543.0
}, {
  "first_name" : "Zoe",
  "last_name" : "O'Kelly",
  "date_time" : "2022-12-12T05:06:32.694+00:00",
  "type" : "RECKLESS",
  "fine_amount" : 784.0
}, {
  "first_name" : "Maxwell",
  "last_name" : "Davies",
  "date_time" : "2023-11-08T05:32:44.694+00:00",
  "type" : "INVALID_LICENSE",
  "fine_amount" : 888.0
}, {
  "first_name" : "Arthur",
  "last_name" : "White",
  "date_time" : "2023-04-22T06:30:07.694+00:00",
  "type" : "FELONY",
  "fine_amount" : 830.0
}, {
  "first_name" : "Isabella",
  "last_name" : "Brown",
  "date_time" : "2023-10-13T15:34:14.694+00:00",
  "type" : "INVALID_LICENSE",
  "fine_amount" : 739.0
}, {
  "first_name" : "Harry",
  "last_name" : "Wilson",
  "date_time" : "2023-05-13T05:44:24.694+00:00",
  "type" : "RED_LIGHT_RUN",
  "fine_amount" : 768.0
}, {
  "first_name" : "Ivan",
  "last_name" : "Johnson",
  "date_time" : "2023-10-03T13:06:52.694+00:00",
  "type" : "RECKLESS",
  "fine_amount" : 851.0
}, {
  "first_name" : "Isabella",
  "last_name" : "Jackson",
  "date_time" : "2023-11-13T20:30:51.694+00:00",
  "type" : "YIELD_FAIL",
  "fine_amount" : 839.0
}, {
  "first_name" : "William",
  "last_name" : "Wilson",
  "date_time" : "2023-05-24T15:05:28.694+00:00",
  "type" : "RED_LIGHT_RUN",
  "fine_amount" : 922.0
}, {
  "first_name" : "Jack",
  "last_name" : "Wilson",
  "date_time" : "2023-01-16T07:45:52.694+00:00",
  "type" : "INVALID_LICENSE",
  "fine_amount" : 910.0
}, {
  "first_name" : "Mark",
  "last_name" : "O'Connor",
  "date_time" : "2023-08-09T19:24:40.694+00:00",
  "type" : "YIELD_FAIL",
  "fine_amount" : 651.0
}, {
  "first_name" : "Harry",
  "last_name" : "Robinson",
  "date_time" : "2023-08-19T12:16:22.694+00:00",
  "type" : "INVALID_LICENSE",
  "fine_amount" : 531.0
}, {
  "first_name" : "Jack",
  "last_name" : "Robinson",
  "date_time" : "2023-11-11T16:39:24.694+00:00",
  "type" : "YIELD_FAIL",
  "fine_amount" : 696.0
}, {
  "first_name" : "Isabella",
  "last_name" : "O'Brien",
  "date_time" : "2023-06-23T07:01:50.694+00:00",
  "type" : "YIELD_FAIL",
  "fine_amount" : 696.0
}, {
  "first_name" : "Jack",
  "last_name" : "Black",
  "date_time" : "2023-04-05T03:27:31.694+00:00",
  "type" : "RED_LIGHT_RUN",
  "fine_amount" : 649.0
}, {
  "first_name" : "Constantine",
  "last_name" : "Davis",
  "date_time" : "2023-05-04T04:47:06.694+00:00",
  "type" : "FELONY",
  "fine_amount" : 613.0
}, {
  "first_name" : "Jane",
  "last_name" : "Davies",
  "date_time" : "2023-02-19T01:35:24.694+00:00",
  "type" : "FELONY",
  "fine_amount" : 967.0
}, {
  "first_name" : "Taylor",
  "last_name" : "White",
  "date_time" : "2023-02-01T12:31:21.694+00:00",
  "type" : "YIELD_FAIL",
  "fine_amount" : 752.0
}, {
  "first_name" : "William",
  "last_name" : "Wilson",
  "date_time" : "2023-05-06T01:19:24.694+00:00",
  "type" : "INVALID_LICENSE",
  "fine_amount" : 748.0
}, {
  "first_name" : "Constantine",
  "last_name" : "Black",
  "date_time" : "2023-07-16T13:18:38.694+00:00",
  "type" : "YIELD_FAIL",
  "fine_amount" : 985.0
}, {
  "first_name" : "Oscar",
  "last_name" : "Davies",
  "date_time" : "2023-02-20T04:40:54.694+00:00",
  "type" : "YIELD_FAIL",
  "fine_amount" : 955.0
}, {
  "first_name" : "Joe",
  "last_name" : "O'Brien",
  "date_time" : "2023-09-09T12:21:48.694+00:00",
  "type" : "FELONY",
  "fine_amount" : 840.0
}, {
  "first_name" : "Oliver",
  "last_name" : "Peterson",
  "date_time" : "2023-06-15T08:48:22.694+00:00",
  "type" : "RED_LIGHT_RUN",
  "fine_amount" : 762.0
}, {
  "first_name" : "Jacob",
  "last_name" : "Taylor",
  "date_time" : "2023-02-03T23:06:22.694+00:00",
  "type" : "YIELD_FAIL",
  "fine_amount" : 557.0
}, {
  "first_name" : "Jean",
  "last_name" : "Davis",
  "date_time" : "2023-01-20T19:06:26.694+00:00",
  "type" : "UNDER_INFLUENCE",
  "fine_amount" : 743.0
}, {
  "first_name" : "Charlie",
  "last_name" : "O'Kelly",
  "date_time" : "2023-05-11T07:55:23.694+00:00",
  "type" : "INVALID_LICENSE",
  "fine_amount" : 601.0
}, {
  "first_name" : "James",
  "last_name" : "Johnson",
  "date_time" : "2023-06-16T17:40:42.694+00:00",
  "type" : "YIELD_FAIL",
  "fine_amount" : 590.0
}, {
  "first_name" : "Maxwell",
  "last_name" : "Roberts",
  "date_time" : "2023-05-22T12:43:50.694+00:00",
  "type" : "RECKLESS",
  "fine_amount" : 790.0
}, {
  "first_name" : "Emily",
  "last_name" : "Black",
  "date_time" : "2023-10-13T17:44:29.694+00:00",
  "type" : "RED_LIGHT_RUN",
  "fine_amount" : 606.0
}, {
  "first_name" : "Jane",
  "last_name" : "Roberts",
  "date_time" : "2022-12-03T05:39:05.694+00:00",
  "type" : "FELONY",
  "fine_amount" : 869.0
}, {
  "first_name" : "Emily",
  "last_name" : "Smith",
  "date_time" : "2023-01-19T06:38:57.694+00:00",
  "type" : "INVALID_LICENSE",
  "fine_amount" : 984.0
}, {
  "first_name" : "James",
  "last_name" : "O'Connor",
  "date_time" : "2023-02-08T02:56:05.694+00:00",
  "type" : "FELONY",
  "fine_amount" : 776.0
}, {
  "first_name" : "Louis",
  "last_name" : "Brown",
  "date_time" : "2023-01-18T09:45:10.694+00:00",
  "type" : "RECKLESS",
  "fine_amount" : 664.0
}, {
  "first_name" : "Jane",
  "last_name" : "Blake",
  "date_time" : "2023-06-24T04:50:49.694+00:00",
  "type" : "YIELD_FAIL",
  "fine_amount" : 927.0
}, {
  "first_name" : "John",
  "last_name" : "Blake",
  "date_time" : "2023-08-15T22:47:18.694+00:00",
  "type" : "RECKLESS",
  "fine_amount" : 656.0
}, {
  "first_name" : "Zoe",
  "last_name" : "O'Kelly",
  "date_time" : "2023-07-30T11:07:02.694+00:00",
  "type" : "RED_LIGHT_RUN",
  "fine_amount" : 787.0
}, {
  "first_name" : "Oscar",
  "last_name" : "White",
  "date_time" : "2023-03-15T15:07:54.694+00:00",
  "type" : "FELONY",
  "fine_amount" : 986.0
}, {
  "first_name" : "Charles",
  "last_name" : "Archer",
  "date_time" : "2023-10-16T10:14:47.694+00:00",
  "type" : "UNDER_INFLUENCE",
  "fine_amount" : 680.0
}, {
  "first_name" : "George",
  "last_name" : "Blake",
  "date_time" : "2022-12-13T08:27:23.694+00:00",
  "type" : "UNDER_INFLUENCE",
  "fine_amount" : 918.0
}, {
  "first_name" : "Harry",
  "last_name" : "Black",
  "date_time" : "2023-10-10T18:18:32.694+00:00",
  "type" : "YIELD_FAIL",
  "fine_amount" : 847.0
}, {
  "first_name" : "Jean",
  "last_name" : "O'Kelly",
  "date_time" : "2023-05-11T22:04:07.694+00:00",
  "type" : "RED_LIGHT_RUN",
  "fine_amount" : 566.0
}, {
  "first_name" : "Ivan",
  "last_name" : "Evans",
  "date_time" : "2023-03-30T18:08:56.694+00:00",
  "type" : "FELONY",
  "fine_amount" : 541.0
}, {
  "first_name" : "Daniela",
  "last_name" : "O'Neill",
  "date_time" : "2023-03-30T10:14:07.694+00:00",
  "type" : "UNDER_INFLUENCE",
  "fine_amount" : 790.0
}, {
  "first_name" : "Charlie",
  "last_name" : "Roberts",
  "date_time" : "2023-09-30T16:10:07.694+00:00",
  "type" : "YIELD_FAIL",
  "fine_amount" : 806.0
}, {
  "first_name" : "William",
  "last_name" : "Peterson",
  "date_time" : "2023-02-18T13:54:00.694+00:00",
  "type" : "RED_LIGHT_RUN",
  "fine_amount" : 789.0
}, {
  "first_name" : "John",
  "last_name" : "Smith",
  "date_time" : "2023-01-10T17:34:49.694+00:00",
  "type" : "INVALID_LICENSE",
  "fine_amount" : 952.0
}, {
  "first_name" : "Charlie",
  "last_name" : "Roberts",
  "date_time" : "2023-07-31T17:14:38.694+00:00",
  "type" : "YIELD_FAIL",
  "fine_amount" : 673.0
}, {
  "first_name" : "Jean",
  "last_name" : "Johnson",
  "date_time" : "2023-11-26T14:35:36.694+00:00",
  "type" : "FELONY",
  "fine_amount" : 546.0
}, {
  "first_name" : "James",
  "last_name" : "Evans",
  "date_time" : "2022-12-05T03:02:14.694+00:00",
  "type" : "INVALID_LICENSE",
  "fine_amount" : 584.0
}, {
  "first_name" : "Daniel",
  "last_name" : "Robinson",
  "date_time" : "2023-08-05T08:51:23.694+00:00",
  "type" : "RECKLESS",
  "fine_amount" : 855.0
}, {
  "first_name" : "Thomas",
  "last_name" : "White",
  "date_time" : "2023-10-30T18:08:02.694+00:00",
  "type" : "RECKLESS",
  "fine_amount" : 620.0
}, {
  "first_name" : "John",
  "last_name" : "Black",
  "date_time" : "2023-11-15T00:30:40.694+00:00",
  "type" : "UNDER_INFLUENCE",
  "fine_amount" : 633.0
}, {
  "first_name" : "Amelia",
  "last_name" : "Peterson",
  "date_time" : "2023-05-25T08:27:41.694+00:00",
  "type" : "RED_LIGHT_RUN",
  "fine_amount" : 515.0
}, {
  "first_name" : "Isabella",
  "last_name" : "White",
  "date_time" : "2023-01-04T19:55:22.695+00:00",
  "type" : "UNDER_INFLUENCE",
  "fine_amount" : 504.0
}, {
  "first_name" : "Oscar",
  "last_name" : "Davis",
  "date_time" : "2023-09-27T07:10:37.695+00:00",
  "type" : "UNDER_INFLUENCE",
  "fine_amount" : 693.0
}, {
  "first_name" : "Jack",
  "last_name" : "Robinson",
  "date_time" : "2023-10-17T05:00:37.695+00:00",
  "type" : "INVALID_LICENSE",
  "fine_amount" : 982.0
}, {
  "first_name" : "Emily",
  "last_name" : "Roberts",
  "date_time" : "2023-06-20T18:57:31.695+00:00",
  "type" : "UNDER_INFLUENCE",
  "fine_amount" : 673.0
}, {
  "first_name" : "Charlie",
  "last_name" : "Smith",
  "date_time" : "2023-10-01T18:29:50.695+00:00",
  "type" : "YIELD_FAIL",
  "fine_amount" : 869.0
}, {
  "first_name" : "Ivan",
  "last_name" : "Archer",
  "date_time" : "2022-12-30T09:33:53.695+00:00",
  "type" : "UNDER_INFLUENCE",
  "fine_amount" : 951.0
}, {
  "first_name" : "Thomas",
  "last_name" : "O'Neill",
  "date_time" : "2023-10-23T23:22:46.695+00:00",
  "type" : "INVALID_LICENSE",
  "fine_amount" : 790.0
}, {
  "first_name" : "William",
  "last_name" : "Taylor",
  "date_time" : "2023-01-10T14:46:59.695+00:00",
  "type" : "UNDER_INFLUENCE",
  "fine_amount" : 942.0
}, {
  "first_name" : "John",
  "last_name" : "Brown",
  "date_time" : "2023-08-05T16:51:05.695+00:00",
  "type" : "YIELD_FAIL",
  "fine_amount" : 814.0
}, {
  "first_name" : "Louis",
  "last_name" : "Wilson",
  "date_time" : "2023-09-22T00:03:21.695+00:00",
  "type" : "RECKLESS",
  "fine_amount" : 683.0
}, {
  "first_name" : "Jack",
  "last_name" : "Peterson",
  "date_time" : "2023-03-23T02:00:44.695+00:00",
  "type" : "INVALID_LICENSE",
  "fine_amount" : 656.0
}, {
  "first_name" : "Jacob",
  "last_name" : "Robinson",
  "date_time" : "2023-03-05T18:29:47.695+00:00",
  "type" : "RED_LIGHT_RUN",
  "fine_amount" : 770.0
}, {
  "first_name" : "Amelia",
  "last_name" : "Robinson",
  "date_time" : "2023-10-31T03:50:32.695+00:00",
  "type" : "YIELD_FAIL",
  "fine_amount" : 775.0
}, {
  "first_name" : "Isla",
  "last_name" : "Davies",
  "date_time" : "2023-01-05T04:23:28.695+00:00",
  "type" : "FELONY",
  "fine_amount" : 553.0
}, {
  "first_name" : "Daniel",
  "last_name" : "Blake",
  "date_time" : "2023-03-13T23:40:39.695+00:00",
  "type" : "RED_LIGHT_RUN",
  "fine_amount" : 998.0
}, {
  "first_name" : "Amelia",
  "last_name" : "Johnson",
  "date_time" : "2023-10-27T03:48:01.695+00:00",
  "type" : "YIELD_FAIL",
  "fine_amount" : 573.0
}, {
  "first_name" : "Constantine",
  "last_name" : "Johnson",
  "date_time" : "2023-08-15T21:04:24.695+00:00",
  "type" : "RED_LIGHT_RUN",
  "fine_amount" : 670.0
}, {
  "first_name" : "George",
  "last_name" : "Wilson",
  "date_time" : "2023-11-11T18:28:23.695+00:00",
  "type" : "UNDER_INFLUENCE",
  "fine_amount" : 672.0
}, {
  "first_name" : "Jean",
  "last_name" : "Johnson",
  "date_time" : "2023-04-06T05:55:46.695+00:00",
  "type" : "RED_LIGHT_RUN",
  "fine_amount" : 907.0
}, {
  "first_name" : "Emily",
  "last_name" : "Johnson",
  "date_time" : "2023-02-26T04:48:54.695+00:00",
  "type" : "INVALID_LICENSE",
  "fine_amount" : 806.0
}, {
  "first_name" : "Daniel",
  "last_name" : "Blake",
  "date_time" : "2023-06-11T17:30:53.695+00:00",
  "type" : "FELONY",
  "fine_amount" : 824.0
}, {
  "first_name" : "Oliver",
  "last_name" : "Archer",
  "date_time" : "2023-02-11T16:56:36.695+00:00",
  "type" : "FELONY",
  "fine_amount" : 643.0
}, {
  "first_name" : "Oliver",
  "last_name" : "Wilson",
  "date_time" : "2023-09-24T22:13:36.695+00:00",
  "type" : "RECKLESS",
  "fine_amount" : 626.0
}, {
  "first_name" : "Arthur",
  "last_name" : "Robinson",
  "date_time" : "2023-07-07T14:07:32.695+00:00",
  "type" : "RECKLESS",
  "fine_amount" : 735.0
}, {
  "first_name" : "Charlie",
  "last_name" : "Evans",
  "date_time" : "2023-10-24T05:18:42.695+00:00",
  "type" : "UNDER_INFLUENCE",
  "fine_amount" : 907.0
}, {
  "first_name" : "Harry",
  "last_name" : "Evans",
  "date_time" : "2023-09-19T05:16:18.695+00:00",
  "type" : "RED_LIGHT_RUN",
  "fine_amount" : 595.0
}, {
  "first_name" : "Max",
  "last_name" : "Wilson",
  "date_time" : "2023-02-20T23:36:40.695+00:00",
  "type" : "FELONY",
  "fine_amount" : 676.0
}, {
  "first_name" : "Daniel",
  "last_name" : "Davis",
  "date_time" : "2022-12-28T21:46:30.695+00:00",
  "type" : "YIELD_FAIL",
  "fine_amount" : 772.0
}, {
  "first_name" : "Arthur",
  "last_name" : "Taylor",
  "date_time" : "2023-01-27T11:58:33.695+00:00",
  "type" : "UNDER_INFLUENCE",
  "fine_amount" : 691.0
}, {
  "first_name" : "Jean",
  "last_name" : "O'Neill",
  "date_time" : "2023-01-05T00:46:54.695+00:00",
  "type" : "FELONY",
  "fine_amount" : 684.0
}, {
  "first_name" : "Jacob",
  "last_name" : "Archer",
  "date_time" : "2023-04-01T22:49:33.695+00:00",
  "type" : "YIELD_FAIL",
  "fine_amount" : 656.0
}, {
  "first_name" : "Thomas",
  "last_name" : "Johnson",
  "date_time" : "2023-02-20T13:29:39.695+00:00",
  "type" : "FELONY",
  "fine_amount" : 768.0
}, {
  "first_name" : "Max",
  "last_name" : "Archer",
  "date_time" : "2023-11-25T03:20:10.695+00:00",
  "type" : "UNDER_INFLUENCE",
  "fine_amount" : 705.0
}, {
  "first_name" : "Louis",
  "last_name" : "Jackson",
  "date_time" : "2023-07-19T16:45:44.695+00:00",
  "type" : "FELONY",
  "fine_amount" : 893.0
}, {
  "first_name" : "Zoe",
  "last_name" : "White",
  "date_time" : "2023-08-29T22:16:28.695+00:00",
  "type" : "RECKLESS",
  "fine_amount" : 737.0
}, {
  "first_name" : "Jane",
  "last_name" : "Davies",
  "date_time" : "2023-01-25T11:00:08.695+00:00",
  "type" : "RECKLESS",
  "fine_amount" : 877.0
}, {
  "first_name" : "Isabella",
  "last_name" : "Davies",
  "date_time" : "2023-04-13T01:20:13.695+00:00",
  "type" : "YIELD_FAIL",
  "fine_amount" : 903.0
}, {
  "first_name" : "Daniel",
  "last_name" : "Taylor",
  "date_time" : "2023-04-08T09:21:22.695+00:00",
  "type" : "RECKLESS",
  "fine_amount" : 522.0
}, {
  "first_name" : "Maxwell",
  "last_name" : "Archer",
  "date_time" : "2023-02-25T23:35:48.695+00:00",
  "type" : "INVALID_LICENSE",
  "fine_amount" : 858.0
}, {
  "first_name" : "Daniel",
  "last_name" : "Peterson",
  "date_time" : "2023-04-08T13:06:35.695+00:00",
  "type" : "INVALID_LICENSE",
  "fine_amount" : 731.0
}, {
  "first_name" : "Jane",
  "last_name" : "White",
  "date_time" : "2023-03-19T02:17:40.695+00:00",
  "type" : "YIELD_FAIL",
  "fine_amount" : 866.0
}, {
  "first_name" : "William",
  "last_name" : "O'Kelly",
  "date_time" : "2023-11-13T12:46:04.695+00:00",
  "type" : "YIELD_FAIL",
  "fine_amount" : 972.0
}, {
  "first_name" : "Jacob",
  "last_name" : "O'Kelly",
  "date_time" : "2023-11-10T14:16:53.695+00:00",
  "type" : "UNDER_INFLUENCE",
  "fine_amount" : 768.0
}, {
  "first_name" : "Joe",
  "last_name" : "O'Connor",
  "date_time" : "2023-07-02T03:47:36.695+00:00",
  "type" : "RECKLESS",
  "fine_amount" : 830.0
}, {
  "first_name" : "Oscar",
  "last_name" : "Roberts",
  "date_time" : "2023-01-01T08:23:44.695+00:00",
  "type" : "INVALID_LICENSE",
  "fine_amount" : 751.0
}, {
  "first_name" : "Isla",
  "last_name" : "Johnson",
  "date_time" : "2023-07-09T12:19:51.695+00:00",
  "type" : "UNDER_INFLUENCE",
  "fine_amount" : 821.0
}, {
  "first_name" : "Daniel",
  "last_name" : "Smith",
  "date_time" : "2023-01-20T23:01:15.695+00:00",
  "type" : "UNDER_INFLUENCE",
  "fine_amount" : 836.0
}, {
  "first_name" : "Jean",
  "last_name" : "Roberts",
  "date_time" : "2023-03-10T04:40:34.695+00:00",
  "type" : "RED_LIGHT_RUN",
  "fine_amount" : 958.0
}, {
  "first_name" : "Charlie",
  "last_name" : "Smith",
  "date_time" : "2023-01-30T01:32:17.695+00:00",
  "type" : "FELONY",
  "fine_amount" : 691.0
}, {
  "first_name" : "William",
  "last_name" : "Wilson",
  "date_time" : "2023-02-12T17:17:30.695+00:00",
  "type" : "FELONY",
  "fine_amount" : 666.0
}, {
  "first_name" : "Jean",
  "last_name" : "Black",
  "date_time" : "2023-11-26T23:43:09.695+00:00",
  "type" : "UNDER_INFLUENCE",
  "fine_amount" : 929.0
}, {
  "first_name" : "Joe",
  "last_name" : "Davies",
  "date_time" : "2023-11-07T05:40:20.695+00:00",
  "type" : "RED_LIGHT_RUN",
  "fine_amount" : 635.0
}, {
  "first_name" : "Oliver",
  "last_name" : "Davies",
  "date_time" : "2023-06-28T04:07:32.695+00:00",
  "type" : "UNDER_INFLUENCE",
  "fine_amount" : 878.0
}, {
  "first_name" : "Constantine",
  "last_name" : "Johnson",
  "date_time" : "2023-09-17T18:03:24.695+00:00",
  "type" : "UNDER_INFLUENCE",
  "fine_amount" : 881.0
}, {
  "first_name" : "Arthur",
  "last_name" : "Davis",
  "date_time" : "2023-09-22T11:34:55.695+00:00",
  "type" : "YIELD_FAIL",
  "fine_amount" : 661.0
}, {
  "first_name" : "Max",
  "last_name" : "Davis",
  "date_time" : "2023-03-27T00:36:40.695+00:00",
  "type" : "YIELD_FAIL",
  "fine_amount" : 936.0
}, {
  "first_name" : "Thomas",
  "last_name" : "O'Kelly",
  "date_time" : "2023-10-01T12:45:57.695+00:00",
  "type" : "RECKLESS",
  "fine_amount" : 746.0
}, {
  "first_name" : "Arthur",
  "last_name" : "Brown",
  "date_time" : "2023-10-24T00:59:18.695+00:00",
  "type" : "RED_LIGHT_RUN",
  "fine_amount" : 659.0
}, {
  "first_name" : "Isla",
  "last_name" : "O'Connor",
  "date_time" : "2023-06-10T01:17:16.695+00:00",
  "type" : "UNDER_INFLUENCE",
  "fine_amount" : 565.0
}, {
  "first_name" : "Oliver",
  "last_name" : "O'Kelly",
  "date_time" : "2022-12-20T12:07:18.695+00:00",
  "type" : "INVALID_LICENSE",
  "fine_amount" : 696.0
}, {
  "first_name" : "Zoe",
  "last_name" : "Black",
  "date_time" : "2023-09-01T05:47:45.695+00:00",
  "type" : "UNDER_INFLUENCE",
  "fine_amount" : 505.0
}, {
  "first_name" : "Arthur",
  "last_name" : "Davies",
  "date_time" : "2023-10-14T19:50:54.695+00:00",
  "type" : "INVALID_LICENSE",
  "fine_amount" : 604.0
}, {
  "first_name" : "Daniela",
  "last_name" : "O'Neill",
  "date_time" : "2023-09-15T02:11:48.695+00:00",
  "type" : "INVALID_LICENSE",
  "fine_amount" : 917.0
}, {
  "first_name" : "James",
  "last_name" : "Robinson",
  "date_time" : "2023-10-19T00:26:25.695+00:00",
  "type" : "UNDER_INFLUENCE",
  "fine_amount" : 718.0
}, {
  "first_name" : "Daniela",
  "last_name" : "Jackson",
  "date_time" : "2023-09-12T15:13:51.695+00:00",
  "type" : "INVALID_LICENSE",
  "fine_amount" : 536.0
}, {
  "first_name" : "Amelia",
  "last_name" : "O'Brien",
  "date_time" : "2023-09-14T05:07:01.695+00:00",
  "type" : "INVALID_LICENSE",
  "fine_amount" : 913.0
}, {
  "first_name" : "Amelia",
  "last_name" : "Black",
  "date_time" : "2023-11-08T21:22:04.695+00:00",
  "type" : "UNDER_INFLUENCE",
  "fine_amount" : 527.0
}, {
  "first_name" : "Mark",
  "last_name" : "O'Neill",
  "date_time" : "2023-08-08T05:51:15.695+00:00",
  "type" : "UNDER_INFLUENCE",
  "fine_amount" : 585.0
}, {
  "first_name" : "James",
  "last_name" : "O'Neill",
  "date_time" : "2022-12-14T11:30:14.695+00:00",
  "type" : "RECKLESS",
  "fine_amount" : 513.0
}, {
  "first_name" : "Isla",
  "last_name" : "Johnson",
  "date_time" : "2023-07-11T16:39:45.695+00:00",
  "type" : "YIELD_FAIL",
  "fine_amount" : 800.0
}, {
  "first_name" : "Arthur",
  "last_name" : "Taylor",
  "date_time" : "2023-03-03T22:01:04.695+00:00",
  "type" : "UNDER_INFLUENCE",
  "fine_amount" : 544.0
}, {
  "first_name" : "Harry",
  "last_name" : "Black",
  "date_time" : "2023-10-05T10:39:41.695+00:00",
  "type" : "FELONY",
  "fine_amount" : 551.0
}, {
  "first_name" : "Zoe",
  "last_name" : "Peterson",
  "date_time" : "2023-07-09T23:23:30.695+00:00",
  "type" : "YIELD_FAIL",
  "fine_amount" : 743.0
}, {
  "first_name" : "Zoe",
  "last_name" : "Robinson",
  "date_time" : "2023-10-15T14:03:10.695+00:00",
  "type" : "YIELD_FAIL",
  "fine_amount" : 605.0
}, {
  "first_name" : "Harry",
  "last_name" : "Black",
  "date_time" : "2023-03-18T23:12:47.695+00:00",
  "type" : "YIELD_FAIL",
  "fine_amount" : 603.0
}, {
  "first_name" : "Jack",
  "last_name" : "Roberts",
  "date_time" : "2023-08-24T06:42:23.695+00:00",
  "type" : "UNDER_INFLUENCE",
  "fine_amount" : 861.0
}, {
  "first_name" : "Constantine",
  "last_name" : "Roberts",
  "date_time" : "2023-10-24T04:31:01.695+00:00",
  "type" : "RECKLESS",
  "fine_amount" : 891.0
}, {
  "first_name" : "John",
  "last_name" : "Blake",
  "date_time" : "2023-06-29T03:56:37.695+00:00",
  "type" : "FELONY",
  "fine_amount" : 624.0
}, {
  "first_name" : "Jack",
  "last_name" : "Black",
  "date_time" : "2023-11-24T14:40:58.695+00:00",
  "type" : "UNDER_INFLUENCE",
  "fine_amount" : 998.0
}, {
  "first_name" : "James",
  "last_name" : "Smith",
  "date_time" : "2023-05-09T13:50:27.695+00:00",
  "type" : "RED_LIGHT_RUN",
  "fine_amount" : 739.0
}, {
  "first_name" : "Arthur",
  "last_name" : "Davies",
  "date_time" : "2023-10-19T08:12:01.695+00:00",
  "type" : "YIELD_FAIL",
  "fine_amount" : 616.0
}, {
  "first_name" : "Oliver",
  "last_name" : "O'Connor",
  "date_time" : "2023-03-24T04:48:38.695+00:00",
  "type" : "FELONY",
  "fine_amount" : 573.0
}, {
  "first_name" : "George",
  "last_name" : "Archer",
  "date_time" : "2023-10-10T06:55:42.695+00:00",
  "type" : "FELONY",
  "fine_amount" : 602.0
}, {
  "first_name" : "Charles",
  "last_name" : "White",
  "date_time" : "2023-03-08T15:44:16.695+00:00",
  "type" : "INVALID_LICENSE",
  "fine_amount" : 502.0
}, {
  "first_name" : "Jacob",
  "last_name" : "Archer",
  "date_time" : "2023-08-06T23:46:14.695+00:00",
  "type" : "UNDER_INFLUENCE",
  "fine_amount" : 761.0
}, {
  "first_name" : "Amelia",
  "last_name" : "Archer",
  "date_time" : "2023-03-29T23:07:13.695+00:00",
  "type" : "INVALID_LICENSE",
  "fine_amount" : 937.0
}, {
  "first_name" : "Daniela",
  "last_name" : "Wilson",
  "date_time" : "2023-06-08T02:21:45.695+00:00",
  "type" : "UNDER_INFLUENCE",
  "fine_amount" : 867.0
}, {
  "first_name" : "James",
  "last_name" : "Davies",
  "date_time" : "2023-09-13T14:34:17.695+00:00",
  "type" : "FELONY",
  "fine_amount" : 992.0
}, {
  "first_name" : "Arthur",
  "last_name" : "Brown",
  "date_time" : "2023-08-07T14:24:18.695+00:00",
  "type" : "INVALID_LICENSE",
  "fine_amount" : 849.0
}, {
  "first_name" : "Jane",
  "last_name" : "Robinson",
  "date_time" : "2023-06-19T18:05:44.695+00:00",
  "type" : "RECKLESS",
  "fine_amount" : 761.0
}, {
  "first_name" : "Zoe",
  "last_name" : "Taylor",
  "date_time" : "2023-05-25T10:43:18.695+00:00",
  "type" : "RECKLESS",
  "fine_amount" : 586.0
}, {
  "first_name" : "Jacob",
  "last_name" : "Johnson",
  "date_time" : "2023-09-01T02:30:41.695+00:00",
  "type" : "YIELD_FAIL",
  "fine_amount" : 604.0
}, {
  "first_name" : "William",
  "last_name" : "Smith",
  "date_time" : "2023-06-13T09:21:19.695+00:00",
  "type" : "YIELD_FAIL",
  "fine_amount" : 759.0
}, {
  "first_name" : "Daniela",
  "last_name" : "Wilson",
  "date_time" : "2023-04-11T15:38:04.695+00:00",
  "type" : "UNDER_INFLUENCE",
  "fine_amount" : 746.0
}, {
  "first_name" : "Daniela",
  "last_name" : "Archer",
  "date_time" : "2023-10-21T23:41:29.695+00:00",
  "type" : "UNDER_INFLUENCE",
  "fine_amount" : 758.0
}, {
  "first_name" : "Harry",
  "last_name" : "Davies",
  "date_time" : "2023-07-23T17:03:20.695+00:00",
  "type" : "FELONY",
  "fine_amount" : 585.0
}, {
  "first_name" : "Thomas",
  "last_name" : "O'Brien",
  "date_time" : "2023-07-14T03:10:16.695+00:00",
  "type" : "RED_LIGHT_RUN",
  "fine_amount" : 693.0
}, {
  "first_name" : "Jane",
  "last_name" : "Peterson",
  "date_time" : "2023-03-07T08:07:29.695+00:00",
  "type" : "RED_LIGHT_RUN",
  "fine_amount" : 621.0
}, {
  "first_name" : "Thomas",
  "last_name" : "Smith",
  "date_time" : "2023-03-21T13:59:08.695+00:00",
  "type" : "RED_LIGHT_RUN",
  "fine_amount" : 857.0
}, {
  "first_name" : "Charles",
  "last_name" : "Black",
  "date_time" : "2023-11-19T01:55:04.695+00:00",
  "type" : "YIELD_FAIL",
  "fine_amount" : 523.0
}, {
  "first_name" : "William",
  "last_name" : "Robinson",
  "date_time" : "2023-04-14T08:33:40.695+00:00",
  "type" : "YIELD_FAIL",
  "fine_amount" : 987.0
}, {
  "first_name" : "William",
  "last_name" : "Smith",
  "date_time" : "2023-05-26T10:05:41.695+00:00",
  "type" : "RECKLESS",
  "fine_amount" : 962.0
}, {
  "first_name" : "Charlie",
  "last_name" : "Archer",
  "date_time" : "2023-05-22T08:09:03.695+00:00",
  "type" : "RED_LIGHT_RUN",
  "fine_amount" : 863.0
}, {
  "first_name" : "Maxwell",
  "last_name" : "Robinson",
  "date_time" : "2022-12-24T21:22:53.695+00:00",
  "type" : "RECKLESS",
  "fine_amount" : 703.0
}, {
  "first_name" : "Oliver",
  "last_name" : "Jackson",
  "date_time" : "2023-07-05T20:03:54.695+00:00",
  "type" : "FELONY",
  "fine_amount" : 929.0
}, {
  "first_name" : "Taylor",
  "last_name" : "Taylor",
  "date_time" : "2023-10-16T20:56:41.695+00:00",
  "type" : "UNDER_INFLUENCE",
  "fine_amount" : 551.0
}, {
  "first_name" : "Oscar",
  "last_name" : "Robinson",
  "date_time" : "2023-05-27T17:15:19.695+00:00",
  "type" : "FELONY",
  "fine_amount" : 654.0
}, {
  "first_name" : "William",
  "last_name" : "Roberts",
  "date_time" : "2023-08-02T15:50:35.695+00:00",
  "type" : "RED_LIGHT_RUN",
  "fine_amount" : 988.0
}, {
  "first_name" : "Charles",
  "last_name" : "O'Neill",
  "date_time" : "2023-03-09T22:59:19.695+00:00",
  "type" : "UNDER_INFLUENCE",
  "fine_amount" : 915.0
}, {
  "first_name" : "William",
  "last_name" : "Evans",
  "date_time" : "2023-06-08T15:52:46.695+00:00",
  "type" : "YIELD_FAIL",
  "fine_amount" : 975.0
}, {
  "first_name" : "James",
  "last_name" : "Brown",
  "date_time" : "2023-10-01T15:45:53.695+00:00",
  "type" : "RED_LIGHT_RUN",
  "fine_amount" : 595.0
}, {
  "first_name" : "Isabella",
  "last_name" : "Wilson",
  "date_time" : "2022-12-10T12:29:05.695+00:00",
  "type" : "FELONY",
  "fine_amount" : 536.0
}, {
  "first_name" : "Jacob",
  "last_name" : "Smith",
  "date_time" : "2023-08-17T18:42:28.695+00:00",
  "type" : "UNDER_INFLUENCE",
  "fine_amount" : 635.0
}, {
  "first_name" : "Jack",
  "last_name" : "Jackson",
  "date_time" : "2023-09-07T10:36:20.695+00:00",
  "type" : "UNDER_INFLUENCE",
  "fine_amount" : 819.0
}, {
  "first_name" : "Maxwell",
  "last_name" : "Peterson",
  "date_time" : "2023-11-17T06:22:08.695+00:00",
  "type" : "YIELD_FAIL",
  "fine_amount" : 603.0
}, {
  "first_name" : "Ivan",
  "last_name" : "Jackson",
  "date_time" : "2023-11-30T20:49:52.695+00:00",
  "type" : "UNDER_INFLUENCE",
  "fine_amount" : 873.0
}, {
  "first_name" : "Isla",
  "last_name" : "Black",
  "date_time" : "2023-09-13T00:23:44.695+00:00",
  "type" : "UNDER_INFLUENCE",
  "fine_amount" : 642.0
}, {
  "first_name" : "John",
  "last_name" : "Brown",
  "date_time" : "2023-07-03T00:47:02.695+00:00",
  "type" : "YIELD_FAIL",
  "fine_amount" : 505.0
}, {
  "first_name" : "Arthur",
  "last_name" : "Blake",
  "date_time" : "2023-08-10T10:34:20.695+00:00",
  "type" : "FELONY",
  "fine_amount" : 516.0
}, {
  "first_name" : "Charlie",
  "last_name" : "O'Neill",
  "date_time" : "2023-02-24T08:31:34.695+00:00",
  "type" : "FELONY",
  "fine_amount" : 918.0
}, {
  "first_name" : "Isabella",
  "last_name" : "Davies",
  "date_time" : "2023-10-29T06:14:57.695+00:00",
  "type" : "RED_LIGHT_RUN",
  "fine_amount" : 773.0
}, {
  "first_name" : "Jane",
  "last_name" : "Jackson",
  "date_time" : "2023-05-22T01:41:50.695+00:00",
  "type" : "RECKLESS",
  "fine_amount" : 852.0
}, {
  "first_name" : "Joe",
  "last_name" : "White",
  "date_time" : "2023-04-28T15:46:19.695+00:00",
  "type" : "FELONY",
  "fine_amount" : 553.0
}, {
  "first_name" : "Thomas",
  "last_name" : "O'Connor",
  "date_time" : "2022-12-26T15:08:42.695+00:00",
  "type" : "RED_LIGHT_RUN",
  "fine_amount" : 576.0
}, {
  "first_name" : "Maxwell",
  "last_name" : "Jackson",
  "date_time" : "2023-10-28T07:54:09.695+00:00",
  "type" : "RED_LIGHT_RUN",
  "fine_amount" : 563.0
}, {
  "first_name" : "Isla",
  "last_name" : "Roberts",
  "date_time" : "2023-04-08T02:48:43.695+00:00",
  "type" : "RED_LIGHT_RUN",
  "fine_amount" : 505.0
}, {
  "first_name" : "Harry",
  "last_name" : "Davies",
  "date_time" : "2023-03-14T07:17:21.695+00:00",
  "type" : "INVALID_LICENSE",
  "fine_amount" : 923.0
}, {
  "first_name" : "Constantine",
  "last_name" : "Robinson",
  "date_time" : "2023-07-27T05:00:42.695+00:00",
  "type" : "INVALID_LICENSE",
  "fine_amount" : 981.0
}, {
  "first_name" : "Isabella",
  "last_name" : "Davis",
  "date_time" : "2023-03-29T12:38:31.695+00:00",
  "type" : "FELONY",
  "fine_amount" : 603.0
}, {
  "first_name" : "Joe",
  "last_name" : "Davies",
  "date_time" : "2023-05-01T19:29:28.695+00:00",
  "type" : "RECKLESS",
  "fine_amount" : 666.0
}, {
  "first_name" : "George",
  "last_name" : "Evans",
  "date_time" : "2023-11-06T23:44:00.695+00:00",
  "type" : "YIELD_FAIL",
  "fine_amount" : 882.0
}, {
  "first_name" : "Maxwell",
  "last_name" : "Davis",
  "date_time" : "2023-04-11T16:56:07.695+00:00",
  "type" : "UNDER_INFLUENCE",
  "fine_amount" : 594.0
}, {
  "first_name" : "Oliver",
  "last_name" : "Peterson",
  "date_time" : "2023-10-05T14:20:31.695+00:00",
  "type" : "INVALID_LICENSE",
  "fine_amount" : 672.0
}, {
  "first_name" : "Mark",
  "last_name" : "O'Kelly",
  "date_time" : "2023-11-21T04:55:57.695+00:00",
  "type" : "RECKLESS",
  "fine_amount" : 915.0
}, {
  "first_name" : "Zoe",
  "last_name" : "Brown",
  "date_time" : "2023-09-17T01:30:32.695+00:00",
  "type" : "UNDER_INFLUENCE",
  "fine_amount" : 563.0
}, {
  "first_name" : "William",
  "last_name" : "Jackson",
  "date_time" : "2023-05-24T03:56:29.695+00:00",
  "type" : "RECKLESS",
  "fine_amount" : 897.0
}, {
  "first_name" : "Charles",
  "last_name" : "Archer",
  "date_time" : "2023-05-26T19:18:05.695+00:00",
  "type" : "RECKLESS",
  "fine_amount" : 803.0
}, {
  "first_name" : "George",
  "last_name" : "O'Kelly",
  "date_time" : "2022-12-19T13:11:40.695+00:00",
  "type" : "FELONY",
  "fine_amount" : 785.0
}, {
  "first_name" : "Taylor",
  "last_name" : "Davis",
  "date_time" : "2023-02-13T13:38:17.695+00:00",
  "type" : "RECKLESS",
  "fine_amount" : 706.0
}, {
  "first_name" : "Zoe",
  "last_name" : "Davis",
  "date_time" : "2023-09-11T02:35:23.695+00:00",
  "type" : "UNDER_INFLUENCE",
  "fine_amount" : 572.0
}, {
  "first_name" : "Amelia",
  "last_name" : "Jackson",
  "date_time" : "2023-09-04T18:02:10.695+00:00",
  "type" : "RECKLESS",
  "fine_amount" : 904.0
} ]